{
	"lastModified":"10/03/2016 05:03:28",
	"nodes":[
		{
			"name":"TrivialSampleAssets",
			"id":"0029e344-d4c5-44cb-8483-4c225edce8c4",
			"kind":"LOADER_GUI",
			"inputPoints":[
				
			],
			"outputPoints":[
				{
					"id":"1fa32ec1-1580-4c46-94b2-d6723cbd19a1",
					"label":"+"
				}
			],
			"pos":{
				"x":40,
				"y":43
			},
			"loadPath":{
				"Unknown":"AssetBundleSample"
			}
		},
		{
			"name":"Filter0",
			"id":"cb8a514e-54bf-43ff-8deb-f8de287a3eda",
			"kind":"FILTER_GUI",
			"inputPoints":[
				{
					"id":"f5b50db8-b46d-47d5-b9fc-35bd8ed5ca90",
					"label":"-"
				}
			],
			"outputPoints":[
				{
					"id":"26e2c49e-41b0-4c9e-8a8e-5b2c9e96462b",
					"label":"MyCube"
				},
				{
					"id":"c2dc14ba-85a5-4a42-8a9d-7c18139e8e6a",
					"label":"MyMaterial"
				},
				{
					"id":"8815032b-540e-449e-8b1d-19b5e6f6ad73",
					"label":"TestScene"
				}
			],
			"pos":{
				"x":191,
				"y":145
			},
			"filter":[
				{
					"keyword":"MyCube",
					"keytype":"Any",
					"pointId":"26e2c49e-41b0-4c9e-8a8e-5b2c9e96462b"
				},
				{
					"keyword":"MyMaterial",
					"keytype":"Any",
					"pointId":"c2dc14ba-85a5-4a42-8a9d-7c18139e8e6a"
				},
				{
					"keyword":"TestScene",
					"keytype":"UnityEngine.SceneManagement.Scene",
					"pointId":"8815032b-540e-449e-8b1d-19b5e6f6ad73"
				}
			]
		},
		{
			"name":"MyCube Bundle",
			"id":"bd434997-c658-4266-bcac-916c4dc34f8f",
			"kind":"BUNDLECONFIG_GUI",
			"inputPoints":[
				{
					"id":"f23ffc8a-94dc-4fba-8187-708c6f9841dd",
					"label":"-"
				}
			],
			"outputPoints":[
				{
					"id":"7d97365d-c0b2-4742-a72f-70b31af3d932",
					"label":"+"
				}
			],
			"pos":{
				"x":534,
				"y":132
			},
			"bundleNameTemplate":{
				"Unknown":"cube-bundle"
			},
			"variants":[
				
			]
		},
		{
			"name":"MyMaterial Bundle",
			"id":"128d18f5-5ac0-4e5f-9e61-f87904e53cdd",
			"kind":"BUNDLECONFIG_GUI",
			"inputPoints":[
				{
					"id":"8764bdfc-7713-4073-8292-fd063fb7d81f",
					"label":"-"
				}
			],
			"outputPoints":[
				{
					"id":"15542c20-63a7-4653-b2b7-5e76cd708c80",
					"label":"+"
				}
			],
			"pos":{
				"x":518,
				"y":210
			},
			"bundleNameTemplate":{
				"Unknown":"material-bundle"
			},
			"variants":[
				
			]
		},
		{
			"name":"BundleBuilder0",
			"id":"b00b9bb5-7459-436d-8fcc-d751f97b713b",
			"kind":"BUNDLEBUILDER_GUI",
			"inputPoints":[
				{
					"id":"671436ce-cb34-4c4d-8e32-abfba56be0b8",
					"label":"-"
				}
			],
			"outputPoints":[
				{
					"id":"8a3414b9-1603-4d39-8dcc-0785aefe5509",
					"label":"+"
				}
			],
			"pos":{
				"x":1058,
				"y":301
			},
			"enabledBundleOptions":{
				"Unknown":0
			}
		},
		{
			"name":"Exporter0",
			"id":"6a9472af-5969-4287-a02e-b069c83b0b76",
			"kind":"EXPORTER_GUI",
			"inputPoints":[
				{
					"id":"7598bfca-555b-4ee3-8caf-d1e90dd7a76f",
					"label":"-"
				}
			],
			"outputPoints":[
				
			],
			"pos":{
				"x":1307,
				"y":363
			},
			"exportTo":{
				"Unknown":"GraphToolBundles"
			}
		},
		{
			"name":"TestScene Bundle",
			"id":"3016ca37-a478-4a93-9b57-f805e4be863e",
			"kind":"BUNDLECONFIG_GUI",
			"inputPoints":[
				{
					"id":"a4fa48e5-aa6a-4e56-917b-c0e6a83e3be0",
					"label":"-"
				}
			],
			"outputPoints":[
				{
					"id":"4f85d9fd-26ba-410a-8c0d-f457aec2fe13",
					"label":"+"
				}
			],
			"pos":{
				"x":518,
				"y":296
			},
			"bundleNameTemplate":{
				"Unknown":"scene-bundle"
			},
			"variants":[
				
			]
		},
		{
			"name":"Variants",
			"id":"1895acec-42db-4a0f-96f7-9e4d33d71dd1",
			"kind":"LOADER_GUI",
			"inputPoints":[
				
			],
			"outputPoints":[
				{
					"id":"809f29ca-e8ee-409c-9d14-b681f88a60a1",
					"label":"+"
				}
			],
			"pos":{
				"x":32,
				"y":366
			},
			"loadPath":{
				"Unknown":"AssetBundleSample/SampleAssets/Variants"
			}
		},
		{
			"name":"Filter1",
			"id":"6315935d-911d-4d4e-90ce-a3b7a24288a7",
			"kind":"FILTER_GUI",
			"inputPoints":[
				{
					"id":"ca822ae2-0868-4a86-9ed8-cdb79e246fd2",
					"label":"-"
				}
			],
			"outputPoints":[
				{
					"id":"44bed9ec-0fad-45b6-b6a4-f485c4446c54",
					"label":""
				},
				{
					"id":"5b2919f4-7572-4b8f-bf4c-16c0448b8025",
					"label":"HD"
				},
				{
					"id":"ae12b169-c3b0-4d76-8500-76b4a3ba2934",
					"label":"SD"
				}
			],
			"pos":{
				"x":221,
				"y":405
			},
			"filter":[
				{
					"keyword":"",
					"keytype":"UnityEngine.SceneManagement.Scene",
					"pointId":"44bed9ec-0fad-45b6-b6a4-f485c4446c54"
				},
				{
					"keyword":"HD",
					"keytype":"Any",
					"pointId":"5b2919f4-7572-4b8f-bf4c-16c0448b8025"
				},
				{
					"keyword":"SD",
					"keytype":"Any",
					"pointId":"ae12b169-c3b0-4d76-8500-76b4a3ba2934"
				}
			]
		},
		{
			"name":"Scene for Variant",
			"id":"5142b302-d8ec-4a34-bc5e-9138c8268ed9",
			"kind":"BUNDLECONFIG_GUI",
			"inputPoints":[
				{
					"id":"cd8b3f43-7aab-4a83-844b-4441c5e2271f",
					"label":"-"
				}
			],
			"outputPoints":[
				{
					"id":"9d724359-7370-45ed-b203-3e1a00b909ba",
					"label":"+"
				}
			],
			"pos":{
				"x":515,
				"y":375
			},
			"bundleNameTemplate":{
				"Unknown":"variants/variant-scene"
			},
			"variants":[
				
			]
		},
		{
			"name":"MyAssetsVariants",
			"id":"7b20ce0a-43a2-428a-afea-d3236744fe25",
			"kind":"BUNDLECONFIG_GUI",
			"inputPoints":[
				{
					"id":"aaeb2425-679b-47fb-bc92-83315de05002",
					"label":"-"
				},
				{
					"id":"e3a7dde4-9643-45bb-b59e-0d75bd2be473",
					"label":"hd"
				},
				{
					"id":"7a814f92-058c-4c55-ba36-41468447cee2",
					"label":"sd"
				}
			],
			"outputPoints":[
				{
					"id":"8697abe0-41a4-499d-ab21-ef5f6c912691",
					"label":"+"
				}
			],
			"pos":{
				"x":510,
				"y":458
			},
			"bundleNameTemplate":{
				"Unknown":"variants/myassets"
			},
			"variants":[
				{
					"name":"hd",
					"pointId":"e3a7dde4-9643-45bb-b59e-0d75bd2be473"
				},
				{
					"name":"sd",
					"pointId":"7a814f92-058c-4c55-ba36-41468447cee2"
				}
			]
		},
		{
			"name":"Tanks",
			"id":"b30cd3bd-297b-4fbf-94b6-6942d67fcf26",
			"kind":"LOADER_GUI",
			"inputPoints":[
				
			],
			"outputPoints":[
				{
					"id":"59653b9c-447e-4c8c-9ecc-7772d5f9ae6e",
					"label":"+"
				}
			],
			"pos":{
				"x":22,
				"y":609
			},
			"loadPath":{
				"Unknown":"AssetBundleSample/SampleAssets/Tanks"
			}
		},
		{
			"name":"Filter2",
			"id":"b7690895-865e-4773-bc42-b43bc2914feb",
			"kind":"FILTER_GUI",
			"inputPoints":[
				{
					"id":"264951da-992e-4bbf-8e66-d4ace06b8def",
					"label":"-"
				}
			],
			"outputPoints":[
				{
					"id":"403d4e37-68c7-40da-b32e-937c3071d8e0",
					"label":"Danish"
				},
				{
					"id":"ae5d6003-4d0d-491c-96f7-5390ffb6e26f",
					"label":"English"
				},
				{
					"id":"c0e889f6-31e9-44c1-862d-d1edef50b15f",
					"label":"Desert-HD"
				},
				{
					"id":"56ed1c16-05d2-495d-b25a-e132debcb746",
					"label":"Desert-SD"
				},
				{
					"id":"9c4999fc-0f34-4cf5-a096-fe2548deb29e",
					"label":"Normal-HD"
				},
				{
					"id":"0c10567c-7d35-4127-a514-b204aeccd1da",
					"label":"Normal-SD"
				},
				{
					"id":"cc1ccc9a-d59e-4f8a-8cef-52c77b22681f",
					"label":"TanksExample"
				}
			],
			"pos":{
				"x":240,
				"y":648
			},
			"filter":[
				{
					"keyword":"Danish",
					"keytype":"Any",
					"pointId":"403d4e37-68c7-40da-b32e-937c3071d8e0"
				},
				{
					"keyword":"English",
					"keytype":"Any",
					"pointId":"ae5d6003-4d0d-491c-96f7-5390ffb6e26f"
				},
				{
					"keyword":"Desert-HD",
					"keytype":"Any",
					"pointId":"c0e889f6-31e9-44c1-862d-d1edef50b15f"
				},
				{
					"keyword":"Desert-SD",
					"keytype":"Any",
					"pointId":"56ed1c16-05d2-495d-b25a-e132debcb746"
				},
				{
					"keyword":"Normal-HD",
					"keytype":"Any",
					"pointId":"9c4999fc-0f34-4cf5-a096-fe2548deb29e"
				},
				{
					"keyword":"Normal-SD",
					"keytype":"Any",
					"pointId":"0c10567c-7d35-4127-a514-b204aeccd1da"
				},
				{
					"keyword":"TanksExample",
					"keytype":"UnityEngine.SceneManagement.Scene",
					"pointId":"cc1ccc9a-d59e-4f8a-8cef-52c77b22681f"
				}
			]
		},
		{
			"name":"Tanks!!!!!",
			"id":"3b4de6de-292f-437f-87d6-edf0ec8411fb",
			"kind":"BUNDLECONFIG_GUI",
			"inputPoints":[
				{
					"id":"85a29d96-3ba3-4862-a8e7-ed200b326500",
					"label":"-"
				},
				{
					"id":"f62a4dd4-471a-4f78-8e69-643d49f9c833",
					"label":"desert-hd"
				},
				{
					"id":"365c930a-9adc-4a74-976e-bb721bb98963",
					"label":"desert-sd"
				},
				{
					"id":"8291de66-cfe4-44b7-a266-2b64b3f12ec7",
					"label":"normal-hd"
				},
				{
					"id":"56052f2b-cac5-441c-acdf-d2707f03aadf",
					"label":"normal-sd"
				}
			],
			"outputPoints":[
				{
					"id":"2627a767-3dd3-450f-9d39-9791312728f5",
					"label":"+"
				}
			],
			"pos":{
				"x":764,
				"y":658
			},
			"bundleNameTemplate":{
				"Unknown":"tanks-albedo"
			},
			"variants":[
				{
					"name":"desert-hd",
					"pointId":"f62a4dd4-471a-4f78-8e69-643d49f9c833"
				},
				{
					"name":"desert-sd",
					"pointId":"365c930a-9adc-4a74-976e-bb721bb98963"
				},
				{
					"name":"normal-hd",
					"pointId":"8291de66-cfe4-44b7-a266-2b64b3f12ec7"
				},
				{
					"name":"normal-sd",
					"pointId":"56052f2b-cac5-441c-acdf-d2707f03aadf"
				}
			]
		},
		{
			"name":"Banner",
			"id":"588461f7-1c48-44d2-b0e2-f2e04b856481",
			"kind":"BUNDLECONFIG_GUI",
			"inputPoints":[
				{
					"id":"640306d0-9967-45c6-a27c-11191ba4e51a",
					"label":"-"
				},
				{
					"id":"2ac52acf-6a42-4b9c-b0c8-ec8ec4526524",
					"label":"danish"
				},
				{
					"id":"39fe023c-b6cb-49ab-9c00-06b8af33c42e",
					"label":"english"
				}
			],
			"outputPoints":[
				{
					"id":"ecaa1eff-2a3e-483f-95c6-065d202b612e",
					"label":"+"
				}
			],
			"pos":{
				"x":771,
				"y":524
			},
			"bundleNameTemplate":{
				"Unknown":"banner"
			},
			"variants":[
				{
					"name":"danish",
					"pointId":"2ac52acf-6a42-4b9c-b0c8-ec8ec4526524"
				},
				{
					"name":"english",
					"pointId":"39fe023c-b6cb-49ab-9c00-06b8af33c42e"
				}
			]
		},
		{
			"name":"TanksScene",
			"id":"2b72b7d9-8715-46c0-9e07-14ecf89844cc",
			"kind":"BUNDLECONFIG_GUI",
			"inputPoints":[
				{
					"id":"9e4f9727-61ff-43db-a5a2-e53d9be727ae",
					"label":"-"
				}
			],
			"outputPoints":[
				{
					"id":"51369a9c-f263-46a8-a8e8-04a6f3e37b0e",
					"label":"+"
				}
			],
			"pos":{
				"x":913,
				"y":851
			},
			"bundleNameTemplate":{
				"Unknown":"tanks-scene-bundle"
			},
			"variants":[
				
			]
		}
	],
	"connections":[
		{
			"id":"c42af53b-5c0e-4f8e-abaf-373e06ec10e1",
			"label":"+",
			"fromNode":"0029e344-d4c5-44cb-8483-4c225edce8c4",
			"fromNodeConPointId":"1fa32ec1-1580-4c46-94b2-d6723cbd19a1",
			"toNode":"cb8a514e-54bf-43ff-8deb-f8de287a3eda",
			"toNodeConPointId":"f5b50db8-b46d-47d5-b9fc-35bd8ed5ca90"
		},
		{
			"id":"742e6ba9-f7a9-4884-98f5-0a2476fcce37",
			"label":"+",
			"fromNode":"128d18f5-5ac0-4e5f-9e61-f87904e53cdd",
			"fromNodeConPointId":"15542c20-63a7-4653-b2b7-5e76cd708c80",
			"toNode":"b00b9bb5-7459-436d-8fcc-d751f97b713b",
			"toNodeConPointId":"671436ce-cb34-4c4d-8e32-abfba56be0b8"
		},
		{
			"id":"fbc1b66e-8579-4500-a501-287ee15be5dc",
			"label":"+",
			"fromNode":"bd434997-c658-4266-bcac-916c4dc34f8f",
			"fromNodeConPointId":"7d97365d-c0b2-4742-a72f-70b31af3d932",
			"toNode":"b00b9bb5-7459-436d-8fcc-d751f97b713b",
			"toNodeConPointId":"671436ce-cb34-4c4d-8e32-abfba56be0b8"
		},
		{
			"id":"5d3571e8-c653-4164-b833-cae78ed4d1ee",
			"label":"MyCube",
			"fromNode":"cb8a514e-54bf-43ff-8deb-f8de287a3eda",
			"fromNodeConPointId":"26e2c49e-41b0-4c9e-8a8e-5b2c9e96462b",
			"toNode":"bd434997-c658-4266-bcac-916c4dc34f8f",
			"toNodeConPointId":"f23ffc8a-94dc-4fba-8187-708c6f9841dd"
		},
		{
			"id":"f0f7c961-bf42-4298-beca-9be77f0890ba",
			"label":"MyMaterial",
			"fromNode":"cb8a514e-54bf-43ff-8deb-f8de287a3eda",
			"fromNodeConPointId":"c2dc14ba-85a5-4a42-8a9d-7c18139e8e6a",
			"toNode":"128d18f5-5ac0-4e5f-9e61-f87904e53cdd",
			"toNodeConPointId":"8764bdfc-7713-4073-8292-fd063fb7d81f"
		},
		{
			"id":"6eb1ef1a-6318-4fa8-a4e9-ddfb6ce60557",
			"label":"+",
			"fromNode":"b00b9bb5-7459-436d-8fcc-d751f97b713b",
			"fromNodeConPointId":"8a3414b9-1603-4d39-8dcc-0785aefe5509",
			"toNode":"6a9472af-5969-4287-a02e-b069c83b0b76",
			"toNodeConPointId":"7598bfca-555b-4ee3-8caf-d1e90dd7a76f"
		},
		{
			"id":"4f010640-11fd-4fc1-a1c8-f55fd8cf303c",
			"label":"TestScene",
			"fromNode":"cb8a514e-54bf-43ff-8deb-f8de287a3eda",
			"fromNodeConPointId":"8815032b-540e-449e-8b1d-19b5e6f6ad73",
			"toNode":"3016ca37-a478-4a93-9b57-f805e4be863e",
			"toNodeConPointId":"a4fa48e5-aa6a-4e56-917b-c0e6a83e3be0"
		},
		{
			"id":"24480ee1-7032-449d-91aa-58830e263073",
			"label":"+",
			"fromNode":"3016ca37-a478-4a93-9b57-f805e4be863e",
			"fromNodeConPointId":"4f85d9fd-26ba-410a-8c0d-f457aec2fe13",
			"toNode":"b00b9bb5-7459-436d-8fcc-d751f97b713b",
			"toNodeConPointId":"671436ce-cb34-4c4d-8e32-abfba56be0b8"
		},
		{
			"id":"1621fde1-7d9c-4ca6-bf3b-cd9d866b9bb3",
			"label":"+",
			"fromNode":"1895acec-42db-4a0f-96f7-9e4d33d71dd1",
			"fromNodeConPointId":"809f29ca-e8ee-409c-9d14-b681f88a60a1",
			"toNode":"6315935d-911d-4d4e-90ce-a3b7a24288a7",
			"toNodeConPointId":"ca822ae2-0868-4a86-9ed8-cdb79e246fd2"
		},
		{
			"id":"e4c323ed-2a6d-4599-b35e-3a659959ac22",
			"label":"",
			"fromNode":"6315935d-911d-4d4e-90ce-a3b7a24288a7",
			"fromNodeConPointId":"44bed9ec-0fad-45b6-b6a4-f485c4446c54",
			"toNode":"5142b302-d8ec-4a34-bc5e-9138c8268ed9",
			"toNodeConPointId":"cd8b3f43-7aab-4a83-844b-4441c5e2271f"
		},
		{
			"id":"e72d90c7-85ee-4586-a942-029b36875eaf",
			"label":"HD",
			"fromNode":"6315935d-911d-4d4e-90ce-a3b7a24288a7",
			"fromNodeConPointId":"5b2919f4-7572-4b8f-bf4c-16c0448b8025",
			"toNode":"7b20ce0a-43a2-428a-afea-d3236744fe25",
			"toNodeConPointId":"e3a7dde4-9643-45bb-b59e-0d75bd2be473"
		},
		{
			"id":"0b347db8-58c7-4188-b015-91176e5e1a5a",
			"label":"SD",
			"fromNode":"6315935d-911d-4d4e-90ce-a3b7a24288a7",
			"fromNodeConPointId":"ae12b169-c3b0-4d76-8500-76b4a3ba2934",
			"toNode":"7b20ce0a-43a2-428a-afea-d3236744fe25",
			"toNodeConPointId":"7a814f92-058c-4c55-ba36-41468447cee2"
		},
		{
			"id":"4a41d12b-0891-4ce1-bbea-64235a14e180",
			"label":"+",
			"fromNode":"5142b302-d8ec-4a34-bc5e-9138c8268ed9",
			"fromNodeConPointId":"9d724359-7370-45ed-b203-3e1a00b909ba",
			"toNode":"b00b9bb5-7459-436d-8fcc-d751f97b713b",
			"toNodeConPointId":"671436ce-cb34-4c4d-8e32-abfba56be0b8"
		},
		{
			"id":"8bf1a499-6100-43e7-b442-a118e2662bd5",
			"label":"+",
			"fromNode":"7b20ce0a-43a2-428a-afea-d3236744fe25",
			"fromNodeConPointId":"8697abe0-41a4-499d-ab21-ef5f6c912691",
			"toNode":"b00b9bb5-7459-436d-8fcc-d751f97b713b",
			"toNodeConPointId":"671436ce-cb34-4c4d-8e32-abfba56be0b8"
		},
		{
			"id":"72cb9740-f853-4e29-8406-9fa7038d070a",
			"label":"+",
			"fromNode":"b30cd3bd-297b-4fbf-94b6-6942d67fcf26",
			"fromNodeConPointId":"59653b9c-447e-4c8c-9ecc-7772d5f9ae6e",
			"toNode":"b7690895-865e-4773-bc42-b43bc2914feb",
			"toNodeConPointId":"264951da-992e-4bbf-8e66-d4ace06b8def"
		},
		{
			"id":"f9a946a7-ef77-4931-9e3a-1e9486a0a6a7",
			"label":"Danish",
			"fromNode":"b7690895-865e-4773-bc42-b43bc2914feb",
			"fromNodeConPointId":"403d4e37-68c7-40da-b32e-937c3071d8e0",
			"toNode":"588461f7-1c48-44d2-b0e2-f2e04b856481",
			"toNodeConPointId":"2ac52acf-6a42-4b9c-b0c8-ec8ec4526524"
		},
		{
			"id":"96ae4981-b0c9-4124-bf04-e1df19266b90",
			"label":"English",
			"fromNode":"b7690895-865e-4773-bc42-b43bc2914feb",
			"fromNodeConPointId":"ae5d6003-4d0d-491c-96f7-5390ffb6e26f",
			"toNode":"588461f7-1c48-44d2-b0e2-f2e04b856481",
			"toNodeConPointId":"39fe023c-b6cb-49ab-9c00-06b8af33c42e"
		},
		{
			"id":"ed6db540-cf7d-40ba-a04e-d26acd19f1e4",
			"label":"Desert-HD",
			"fromNode":"b7690895-865e-4773-bc42-b43bc2914feb",
			"fromNodeConPointId":"c0e889f6-31e9-44c1-862d-d1edef50b15f",
			"toNode":"3b4de6de-292f-437f-87d6-edf0ec8411fb",
			"toNodeConPointId":"f62a4dd4-471a-4f78-8e69-643d49f9c833"
		},
		{
			"id":"f957abeb-ae2f-4d6f-9a05-2e9d033c4480",
			"label":"Desert-SD",
			"fromNode":"b7690895-865e-4773-bc42-b43bc2914feb",
			"fromNodeConPointId":"56ed1c16-05d2-495d-b25a-e132debcb746",
			"toNode":"3b4de6de-292f-437f-87d6-edf0ec8411fb",
			"toNodeConPointId":"365c930a-9adc-4a74-976e-bb721bb98963"
		},
		{
			"id":"e3790e0e-5a42-4ef8-acb6-37b29fc1e8b0",
			"label":"Normal-HD",
			"fromNode":"b7690895-865e-4773-bc42-b43bc2914feb",
			"fromNodeConPointId":"9c4999fc-0f34-4cf5-a096-fe2548deb29e",
			"toNode":"3b4de6de-292f-437f-87d6-edf0ec8411fb",
			"toNodeConPointId":"8291de66-cfe4-44b7-a266-2b64b3f12ec7"
		},
		{
			"id":"b284a040-66a7-4ebf-afd5-4e7afd9ca27d",
			"label":"Normal-SD",
			"fromNode":"b7690895-865e-4773-bc42-b43bc2914feb",
			"fromNodeConPointId":"0c10567c-7d35-4127-a514-b204aeccd1da",
			"toNode":"3b4de6de-292f-437f-87d6-edf0ec8411fb",
			"toNodeConPointId":"56052f2b-cac5-441c-acdf-d2707f03aadf"
		},
		{
			"id":"f8adfb63-4a14-4235-8357-17c7a8020def",
			"label":"+",
			"fromNode":"588461f7-1c48-44d2-b0e2-f2e04b856481",
			"fromNodeConPointId":"ecaa1eff-2a3e-483f-95c6-065d202b612e",
			"toNode":"b00b9bb5-7459-436d-8fcc-d751f97b713b",
			"toNodeConPointId":"671436ce-cb34-4c4d-8e32-abfba56be0b8"
		},
		{
			"id":"ec154b04-0c56-497c-b27e-a63881c8c82e",
			"label":"+",
			"fromNode":"3b4de6de-292f-437f-87d6-edf0ec8411fb",
			"fromNodeConPointId":"2627a767-3dd3-450f-9d39-9791312728f5",
			"toNode":"b00b9bb5-7459-436d-8fcc-d751f97b713b",
			"toNodeConPointId":"671436ce-cb34-4c4d-8e32-abfba56be0b8"
		},
		{
			"id":"466f1ea1-fc1b-442c-af8e-19ad4e94bf4f",
			"label":"TanksExample",
			"fromNode":"b7690895-865e-4773-bc42-b43bc2914feb",
			"fromNodeConPointId":"cc1ccc9a-d59e-4f8a-8cef-52c77b22681f",
			"toNode":"2b72b7d9-8715-46c0-9e07-14ecf89844cc",
			"toNodeConPointId":"9e4f9727-61ff-43db-a5a2-e53d9be727ae"
		},
		{
			"id":"72450360-5be6-4a4c-a225-1fd0d0e3f4d6",
			"label":"+",
			"fromNode":"2b72b7d9-8715-46c0-9e07-14ecf89844cc",
			"fromNodeConPointId":"51369a9c-f263-46a8-a8e8-04a6f3e37b0e",
			"toNode":"b00b9bb5-7459-436d-8fcc-d751f97b713b",
			"toNodeConPointId":"671436ce-cb34-4c4d-8e32-abfba56be0b8"
		}
	]
}